kora_quickdraw/__init__.py
kora_quickdraw/kora_quickdraw.py
kora_quickdraw-0.0.2.dist-info/LICENSE
kora_quickdraw-0.0.2.dist-info/METADATA
kora_quickdraw-0.0.2.dist-info/WHEEL
kora_quickdraw-0.0.2.dist-info/top_level.txt
kora_quickdraw-0.0.2.dist-info/RECORD
