Metadata-Version: 2.1
Name: kora-quickdraw
Version: 0.0.2
Summary: Quick graph simple matplotlib
Home-page: https://github.com/karnigen/kora_quickdraw
Author: Tony Karnigen
Author-email: karnigen@gmail.com
License: UNKNOWN
Project-URL: Bug Tracker, https://github.com/karnigen/kora_quickdraw/issues
Platform: UNKNOWN
Classifier: Programming Language :: Python :: 3
Classifier: License :: OSI Approved :: MIT License
Classifier: Operating System :: OS Independent
Requires-Python: >=3.6
License-File: LICENSE
